ffr/__init__.py
ffr/filter.py
ffr/login.py
ffr/main.py
ffr-0.0.4.data/scripts/ffr
ffr-0.0.4.dist-info/LICENSE
ffr-0.0.4.dist-info/METADATA
ffr-0.0.4.dist-info/WHEEL
ffr-0.0.4.dist-info/top_level.txt
ffr-0.0.4.dist-info/RECORD
