Metadata-Version: 2.1
Name: ffr
Version: 0.0.4
Summary: Filter for Reddit saves
Home-page: https://github.com/Psycoguana/Filter-for-Reddit
Author: Psycoguana
Author-email: 
License: UNKNOWN
Platform: UNKNOWN
Classifier: Programming Language :: Python :: 3
Classifier: License :: OSI Approved :: Mozilla Public License 2.0 (MPL 2.0)
Classifier: Operating System :: OS Independent
Requires-Python: >=3.6
Requires-Dist: praw
Requires-Dist: rich
Requires-Dist: click
